[
  {
    "title": "Licentia BLACK",
    "description": "Still fucking and cutting heads, just faster.",
    "author": "cacophony",
    "maintainers": [
      "github/cacophony-wj"
    ],
    "game": "skyrimspecialedition",
    "official": true,
    "tags": [
      "Official",
      "Power Fantasy",
      "Vokriinator",
      "CGO",
      "Creation Club",
      "LotD",
      "Performance"
    ],
    "nsfw": true,
    "utility_list": false,
    "image_contains_title": false,
    "force_down": false,
    "links": {
      "image": "https://raw.githubusercontent.com/cacophony-wj/licentia_black/main/images/Transparent-Background-2.png",
      "readme": "https://github.com/cacophony-wj/licentia_black",
      "download": "https://authored-files.wabbajack.org/Licentia BLACK.wabbajack_7ae0c9ca-1454-4db1-9d8e-ac2fc9a9c422",
      "machineURL": "licentia_black",
      "discordURL": "https://discord.gg/jolly-coop"
    },
    "download_metadata": {
      "Hash": "S7hAGEzFdko=",
      "Size": 402518538,
      "NumberOfArchives": 1220,
      "SizeOfArchives": 127472167030,
      "NumberOfInstalledFiles": 272849,
      "SizeOfInstalledFiles": 213131401259
    },
    "version": "5.5.6",
    "dateCreated": "1970-01-01T00:00:00Z",
    "dateUpdated": "2023-02-07T05:18:34.5974611Z",
    "repositoryName": ""
  }
]